iowarp_agents/__init__.py
iowarp_agents/cli.py
iowarp_agents-0.1.0.dist-info/METADATA
iowarp_agents-0.1.0.dist-info/WHEEL
iowarp_agents-0.1.0.dist-info/entry_points.txt
iowarp_agents-0.1.0.dist-info/RECORD
