Metadata-Version: 2.4
Name: iowarp-agents
Version: 0.1.0
Summary: Beautiful CLI for managing IOWarp scientific AI agents
Project-URL: Homepage, https://github.com/iowarp/iowarp-agents
Project-URL: Repository, https://github.com/iowarp/iowarp-agents
Project-URL: Issues, https://github.com/iowarp/iowarp-agents/issues
Project-URL: Documentation, https://iowarp.github.io/iowarp-agents/
Author-email: IOWarp Team <team@iowarp.com>
License-Expression: MIT
Keywords: agents,ai,claude,cli,computing,scientific
Classifier: Development Status :: 4 - Beta
Classifier: Environment :: Console
Classifier: Intended Audience :: Developers
Classifier: Intended Audience :: Science/Research
Classifier: License :: OSI Approved :: MIT License
Classifier: Operating System :: OS Independent
Classifier: Programming Language :: Python :: 3
Classifier: Programming Language :: Python :: 3.8
Classifier: Programming Language :: Python :: 3.9
Classifier: Programming Language :: Python :: 3.10
Classifier: Programming Language :: Python :: 3.11
Classifier: Programming Language :: Python :: 3.12
Classifier: Topic :: Scientific/Engineering
Classifier: Topic :: Software Development :: Libraries :: Python Modules
Classifier: Topic :: System :: Systems Administration
Classifier: Topic :: Utilities
Requires-Python: >=3.8
Requires-Dist: click>=8.0.0
Requires-Dist: requests>=2.25.0
Requires-Dist: rich>=13.0.0
